edsl/__init__.py
edsl/__main__.py
edsl/__version__.py
edsl/agents/__init__.py
edsl/agents/agent.py
edsl/agents/agent_chat.py
edsl/agents/agent_combination.py
edsl/agents/agent_direct_answering.py
edsl/agents/agent_dynamic_traits.py
edsl/agents/agent_from_result.py
edsl/agents/agent_instructions.py
edsl/agents/agent_invigilator.py
edsl/agents/agent_list.py
edsl/agents/agent_list_builder.py
edsl/agents/agent_list_code_generator.py
edsl/agents/agent_list_collection.py
edsl/agents/agent_list_factories.py
edsl/agents/agent_list_filter.py
edsl/agents/agent_list_joiner.py
edsl/agents/agent_list_serializer.py
edsl/agents/agent_list_trait_operations.py
edsl/agents/agent_operations.py
edsl/agents/agent_prompt.py
edsl/agents/agent_serialization.py
edsl/agents/agent_table.py
edsl/agents/agent_trait_manager.py
edsl/agents/agent_traits.py
edsl/agents/agent_traits_manager.py
edsl/agents/descriptors.py
edsl/agents/exceptions.py
edsl/base/__init__.py
edsl/base/base_class.py
edsl/base/base_exception.py
edsl/base/data_transfer_models.py
edsl/base/enums.py
edsl/base/exceptions.py
edsl/base/item_collection_abc.py
edsl/base/pretty_diff.py
edsl/buckets/__init__.py
edsl/buckets/bucket_collection.py
edsl/buckets/exceptions.py
edsl/buckets/model_buckets.py
edsl/buckets/token_bucket.py
edsl/buckets/token_bucket_api.py
edsl/buckets/token_bucket_client.py
edsl/caching/__init__.py
edsl/caching/cache.py
edsl/caching/cache_entry.py
edsl/caching/cache_handler.py
edsl/caching/exceptions.py
edsl/caching/orm.py
edsl/caching/remote_cache_sync.py
edsl/caching/sql_dict.py
edsl/cli.py
edsl/config/__init__.py
edsl/config/config_class.py
edsl/config.py
edsl/conjure/__init__.py
edsl/conversation/Conversation.py
edsl/conversation/__init__.py
edsl/conversation/car_buying.py
edsl/conversation/chips.py
edsl/conversation/exceptions.py
edsl/conversation/mug_negotiation.py
edsl/conversation/next_speaker_utilities.py
edsl/coop/__init__.py
edsl/coop/coop.py
edsl/coop/coop_functions.py
edsl/coop/coop_jobs_objects.py
edsl-1.0.4.dist-info/LICENSE
edsl-1.0.4.dist-info/METADATA
edsl-1.0.4.dist-info/WHEEL
edsl-1.0.4.dist-info/entry_points.txt
edsl-1.0.4.dist-info/RECORD
