Metadata-Version: 2.3
Name: edsl
Version: 1.0.4
Summary: Create and analyze LLM-based surveys
License: MIT
Keywords: LLM,social science,surveys,user research
Author: John Horton
Author-email: info@expectedparrot.com
Requires-Python: >=3.9.1,<3.14
Classifier: License :: OSI Approved :: MIT License
Classifier: Programming Language :: Python :: 3
Classifier: Programming Language :: Python :: 3.10
Classifier: Programming Language :: Python :: 3.11
Classifier: Programming Language :: Python :: 3.12
Classifier: Programming Language :: Python :: 3.13
Classifier: Topic :: Scientific/Engineering :: Artificial Intelligence
Classifier: Topic :: Software Development :: Libraries :: Application Frameworks
Classifier: Topic :: Software Development :: Libraries :: Python Modules
Provides-Extra: screenshots
Provides-Extra: services
Requires-Dist: aiohttp (>=3.9.1,<4.0.0)
Requires-Dist: anthropic (>=0.45.0,<0.46.0)
Requires-Dist: anywidget (>=0.9.18,<0.10.0)
Requires-Dist: azure-ai-inference (>=1.0.0b3,<2.0.0)
Requires-Dist: black[jupyter] (>=24.4.2,<25.0.0)
Requires-Dist: boto3 (>=1.34.161,<2.0.0)
Requires-Dist: fastapi (>=0.112.1,<0.113.0) ; extra == "services"
Requires-Dist: firecrawl-py (>=3.2.1,<4.0.0)
Requires-Dist: google-genai (>=1.30.0,<2.0.0)
Requires-Dist: groq (==0.23.1)
Requires-Dist: jinja2 (>=3.1.2,<4.0.0)
Requires-Dist: json-repair (>=0.28.4,<0.29.0)
Requires-Dist: jupyter (>=1.0.0,<2.0.0)
Requires-Dist: markdown2 (>=2.4.11,<3.0.0)
Requires-Dist: matplotlib (>=3.9.0,<4.0.0)
Requires-Dist: memory-profiler (>=0.61.0,<0.62.0)
Requires-Dist: mistralai (>=1.0.2,<2.0.0)
Requires-Dist: nest-asyncio (>=1.5.9,<2.0.0)
Requires-Dist: numpy (>=1.24.0,<3) ; python_version < "3.13"
Requires-Dist: numpy (>=2.1.0,<3) ; python_version >= "3.13"
Requires-Dist: openai (>=1.4.0,<2.0.0)
Requires-Dist: openpyxl (>=3.1.5,<4.0.0)
Requires-Dist: pandas (>=2.1.4,<3.0.0)
Requires-Dist: platformdirs (>=4.3.6,<5.0.0)
Requires-Dist: pluggy (>=1.3.0,<2.0.0)
Requires-Dist: pydantic-settings (>=2.10.1,<3.0.0)
Requires-Dist: pydot (>=2.0.0,<3.0.0)
Requires-Dist: pygments (>=2.17.2,<3.0.0)
Requires-Dist: pypdf2 (>=3.0.1,<4.0.0)
Requires-Dist: pyreadstat (==1.2.8)
Requires-Dist: python-docx (>=1.1.0,<2.0.0)
Requires-Dist: python-dotenv (>=1.0.0,<2.0.0)
Requires-Dist: python-pptx (>=1.0.2,<2.0.0)
Requires-Dist: restrictedpython (>=7.1,<8.0)
Requires-Dist: rich (>=13.7.0,<14.0.0)
Requires-Dist: setuptools (<72.0)
Requires-Dist: simpleeval (>=0.9.13,<0.10.0)
Requires-Dist: sqlalchemy (>=2.0.23,<3.0.0)
Requires-Dist: tabulate (>=0.9.0,<0.10.0)
Requires-Dist: tenacity (>=8.2.3,<9.0.0)
Requires-Dist: typer[all] (>=0.9.0,<0.10.0)
Requires-Dist: urllib3 (>=1.25.4,<1.27)
Requires-Dist: uvicorn (>=0.30.6,<0.31.0) ; extra == "services"
Project-URL: Documentation, https://docs.expectedparrot.com
Project-URL: Homepage, https://www.expectedparrot.com/
